dummy/__init__.py
dummy/api.py
dummy/middleware.py
dummy/response.py
dummy_framework-0.0.1.dist-info/METADATA
dummy_framework-0.0.1.dist-info/WHEEL
dummy_framework-0.0.1.dist-info/top_level.txt
dummy_framework-0.0.1.dist-info/RECORD
