Metadata-Version: 2.1
Name: dummy-framework
Version: 0.0.1
Summary: Dummy Python Web Framework built for learning purposes.
Author: Byron Machin
Author-email: bmachin7@gmail.com
License: MIT
Classifier: Programming Language :: Python :: 3.6
Requires-Python: >=3.6.0
Requires-Dist: Jinja2==3.1.4
Requires-Dist: WebOb==1.8.8
Requires-Dist: parse==1.20.2
Requires-Dist: requests-wsgi-adapter==0.4.1
Requires-Dist: requests==2.32.3
Requires-Dist: whitenoise==6.7.0
